pivota_agent/__init__.py
pivota_agent/client.py
pivota_agent/compat.py
pivota_agent/exceptions.py
pivota_agent-1.0.0.dist-info/licenses/LICENSE
pivota_agent-1.0.0.dist-info/METADATA
pivota_agent-1.0.0.dist-info/WHEEL
pivota_agent-1.0.0.dist-info/top_level.txt
pivota_agent-1.0.0.dist-info/RECORD
