Metadata-Version: 2.4
Name: pivota-agent
Version: 1.0.0
Summary: Official Python SDK for Pivota Agent API
Home-page: https://github.com/pivota/pivota-agent-sdk-python
Author: Pivota
Author-email: support@pivota.com
Project-URL: Documentation, https://docs.pivota.com/agent-sdk
Project-URL: Source, https://github.com/pivota/pivota-agent-sdk-python
Project-URL: Tracker, https://github.com/pivota/pivota-agent-sdk-python/issues
Keywords: pivota agent ecommerce api sdk payments
Classifier: Development Status :: 4 - Beta
Classifier: Intended Audience :: Developers
Classifier: Topic :: Software Development :: Libraries :: Python Modules
Classifier: License :: OSI Approved :: MIT License
Classifier: Programming Language :: Python :: 3
Classifier: Programming Language :: Python :: 3.8
Classifier: Programming Language :: Python :: 3.9
Classifier: Programming Language :: Python :: 3.10
Classifier: Programming Language :: Python :: 3.11
Classifier: Programming Language :: Python :: 3.12
Requires-Python: >=3.8
License-File: LICENSE
Requires-Dist: requests>=2.25.0
Provides-Extra: dev
Requires-Dist: pytest>=7.0.0; extra == "dev"
Requires-Dist: pytest-asyncio>=0.18.0; extra == "dev"
Requires-Dist: black>=22.0.0; extra == "dev"
Requires-Dist: mypy>=0.950; extra == "dev"
Dynamic: author
Dynamic: author-email
Dynamic: classifier
Dynamic: description
Dynamic: description-content-type
Dynamic: home-page
Dynamic: keywords
Dynamic: license-file
Dynamic: project-url
Dynamic: provides-extra
Dynamic: requires-dist
Dynamic: requires-python
Dynamic: summary
